try2/__init__.py
try2-0.0.4.dist-info/METADATA
try2-0.0.4.dist-info/WHEEL
try2-0.0.4.dist-info/licenses/LICENSE
try2-0.0.4.dist-info/RECORD
